MANIFEST.in
README.rst
setup.py
colinws_todo.egg-info/PKG-INFO
colinws_todo.egg-info/SOURCES.txt
colinws_todo.egg-info/dependency_links.txt
colinws_todo.egg-info/top_level.txt
todo/__init__.py
todo/admin.py
todo/apps.py
todo/models.py
todo/tests.py
todo/urls.py
todo/views.py
todo/static/css/bootstrap-theme.css
todo/static/css/bootstrap-theme.css.map
todo/static/css/bootstrap-theme.min.css
todo/static/css/bootstrap-theme.min.css.map
todo/static/css/bootstrap.css
todo/static/css/bootstrap.css.map
todo/static/css/bootstrap.min.css
todo/static/css/bootstrap.min.css.map
todo/static/css/reset.css
todo/static/css/todo.css
todo/static/css/images/bg_1.png
todo/static/css/images/email.png
todo/static/css/images/home.png
todo/static/css/images/msn.png
todo/static/css/images/ok.gif
todo/static/css/images/qq.png
todo/static/css/images/website.png
todo/static/images/doing.gif
todo/static/images/favicon.ico
todo/static/images/finished.jpg
todo/static/js/bootstrap.js
todo/static/js/bootstrap.min.js
todo/static/js/jquery.min.js
todo/templates/todo/base.html
todo/templates/todo/edit.html
todo/templates/todo/index.html
todo/templates/todo/new.html