Metadata-Version: 1.1
Name: colinws-todo
Version: 0.3
Summary: A simple Django Todo List application
Home-page: https://blog.colinspace.com/
Author: Colin.Liu
Author-email: colinservice@126.com
License: MIT License
Keywords: Colin,colinws,todo,todo list,django
Platform: Linux
Platform: Unix
Classifier: Environment :: Web Environment
Classifier: Framework :: Django
Classifier: Framework :: Django :: 1.11
Classifier: Intended Audience :: Developers
Classifier: License :: OSI Approved :: MIT License
Classifier: Operating System :: OS Independent
Classifier: Programming Language :: Python
Classifier: Programming Language :: Python :: 3
Classifier: Programming Language :: Python :: 3.5
Classifier: Topic :: Internet :: WWW/HTTP
Classifier: Topic :: Internet :: WWW/HTTP :: Dynamic Content
